[{"id":"aa8aaa02.848d88","type":"ibmiot in","z":"79e54b84.5f4484","authentication":"apiKey","apiKey":"af2adcb8.019db","inputType":"cmd","logicalInterface":"","ruleId":"","deviceId":"F1","applicationId":"","deviceType":"DeviceFire","eventType":"+","commandType":"cmd","format":"json","name":"IBM IoT","service":"registered","allDevices":"","allApplications":"","allDeviceTypes":false,"allLogicalInterfaces":"","allEvents":true,"allCommands":"","allFormats":"","qos":0,"x":210,"y":220,"wires":[["e92a0bc8.dede08","75872767.31cb78"]]},{"id":"dbc4edc8.b6de","type":"debug","z":"79e54b84.5f4484","name":"","active":false,"tosidebar":true,"console":false,"tostatus":false,"complete":"false","x":530,"y":200,"wires":[]},{"id":"e92a0bc8.dede08","type":"function","z":"79e54b84.5f4484","name":"Temperature","func":"global.set(\"Temperature\",msg.payload=msg.payload.Temperature)\nmsg.payload=msg.payload.Temperature\nreturn msg;","outputs":1,"noerr":0,"x":350,"y":160,"wires":[["dbc4edc8.b6de","2336bc27.e75574"]]},{"id":"75872767.31cb78","type":"function","z":"79e54b84.5f4484","name":"Gas Levels","func":"msg.payload=meg.payload.Gas\nreturn msg;","outputs":1,"noerr":0,"x":350,"y":280,"wires":[["dbc4edc8.b6de","f6d6882b.f6e7b8"]]},{"id":"2336bc27.e75574","type":"ui_gauge","z":"79e54b84.5f4484","name":"TempReadings","group":"f13a2904.99ca48","order":0,"width":0,"height":0,"gtype":"gage","title":"Temp","label":"Celcius","format":"{{value}}","min":"-20","max":"110","colors":["#00b500","#e6e600","#ca3838"],"seg1":"","seg2":"","x":530,"y":140,"wires":[]},{"id":"f6d6882b.f6e7b8","type":"ui_gauge","z":"79e54b84.5f4484","name":"GasSaturation","group":"f13a2904.99ca48","order":2,"width":0,"height":0,"gtype":"gage","title":"Gas","label":"Units","format":"{{value}}","min":0,"max":"100","colors":["#00b500","#e6e600","#ca3838"],"seg1":"","seg2":"","x":540,"y":260,"wires":[]},{"id":"af2adcb8.019db","type":"ibmiot","z":"","name":"","keepalive":"60","serverName":"","cleansession":true,"appId":"","shared":false},{"id":"f13a2904.99ca48","type":"ui_group","z":"","name":"Default","tab":"e303c287.355c5","order":1,"disp":true,"width":"6","collapse":false},{"id":"e303c287.355c5","type":"ui_tab","z":"","name":"TempReadings","icon":"dashboard","disabled":false,"hidden":false}]